rust_requests-0.1.0b1.dist-info/METADATA
rust_requests-0.1.0b1.dist-info/WHEEL
rust_requests/__init__.py
rust_requests/__init__.pyi
rust_requests/py.typed
rust_requests/rust_requests.cpython-39-x86_64-linux-gnu.so
rust_requests-0.1.0b1.dist-info/RECORD
